{
  "$schema": "https://raw.githubusercontent.com/microsoft/vcpkg-tool/main/docs/vcpkg.schema.json",
  "dependencies": [
    "boost-algorithm",
    "boost-foreach",
    "boost-format",
    "boost-geometry",
    "boost-heap",
    "boost-optional",
    "boost-property-tree",
    "boost-range",
    "boost-tokenizer",
    "curl",
    "cxxopts",
    "date",
    {
      "name": "dirent",
      "platform": "windows"
    },
    {
      "name": "gdal",
      "default-features": false,
      "features": ["recommended-features"]
    },
    "geos",
    "libspatialite",
    "pkgconf",
    "pybind11",
    "rapidjson",
    "spatialite-tools",
    "luajit",
    "lz4",
    "protobuf",
    "sqlite3",
    "zlib"
  ]
}
